FAPSDemonstratorAPI/APIService.py
FAPSDemonstratorAPI/ApplicationConstants.py
FAPSDemonstratorAPI/__init__.py
FAPSDemonstratorAPI/command.py
FAPSDemonstratorAPI/command_mode.py
FAPSDemonstratorAPI/parameter_mode.py
FAPSDemonstratorAPI/program.py
FAPSDemonstratorAPI/utils.py
TransformationMatrix/__init__.py
example/Pick_and_Place_Scenario_01.py
example/__init__.py
example/_calibrate_all_magazin.py
example/_calibrate_camera.py
example/_calibrate_magazin.py
example/_calibrate_product.py
example/_goto_by_segment.py
example/_pickup_object.py
example/_scan_all_magazin.py
example/_scan_magazin.py
example/_scan_product.py
example/_send_dummy_order.py
example/_take_picture_of_magazin_by_segment.py
example/_take_product_picture.py
example/_take_product_picture_processing.py
example/advanced_example.py
example/advanced_example_with_optimizer.py
example/camera_example.py
example/demonstrator_optimizer.py
example/just_picture_example.py
example/main_optimizer.py
example/simple_example.py
FAPSDemonstratorAPI-0.0.7.dist-info/METADATA
FAPSDemonstratorAPI-0.0.7.dist-info/WHEEL
FAPSDemonstratorAPI-0.0.7.dist-info/top_level.txt
FAPSDemonstratorAPI-0.0.7.dist-info/RECORD
